[{"게임명":"게리 모드","평점":"7.5","장르":"시뮬레이션","한글 지원":"미지원","플랫폼":"PC, MAC","가격":"패키지구매","개발사":"페이스펀치 스튜디오","유통사":"밸브 소프트웨어","일정":"[출시] 2006.11.29 (PC)[출시] 2010.09.23 (MAC)","사이트":"http://www.garrysmod.com/"},{"게임명":"에이스 컴뱃: 어썰트 호라이즌","평점":"7.1","장르":"슈팅","한글 지원":"미지원","플랫폼":"PS3, Xbox360","가격":"패키지구매","개발사":"프로젝트 에이스","유통사":"남코 반다이","일정":"[출시] 2011.10.11 (PS3)[출시] 2011.10.11 (Xbox360)","사이트":"http://ah.acecombat.jp/#/top"},{"게임명":"와쿠와쿠 7","평점":"10","장르":"격투","한글 지원":"미지원","플랫폼":"NEOGEO, 새턴, AC","가격":"패키지구매","개발사":"선소프트","유통사":"SNK 플레이모어","일정":"[출시] 1996.11.21 (AC)[출시] 1996.11.21 (NEOGEO)[출시] 1997.06.20 (새턴)","사이트":""},{"게임명":"피파 12","평점":"6.6","장르":"스포츠","한글 지원":"미지원","플랫폼":"PC, PS3, Xbox360, Wii, PS2","가격":"패키지구매","개발사":"EA 캐나다","유통사":"EA","일정":"[출시] 2011.09.27 (PC)[출시] 2011.09.27 (PS3)[출시] 2011.09.27 (PS2)[출시] 2011.09.27 (Xbox360)[출시] 2011.09.26 (Wii)","사이트":"http://www.ea.com/soccer/fifa"},{"게임명":"심즈 소셜","평점":"0","장르":"소셜","한글 지원":"미지원","플랫폼":"웹브라우저","가격":"부분유료화","개발사":"플레이피쉬","유통사":"EA","일정":"[출시] 2011.08.09 (웹브라우저)","사이트":"http://www.facebook.com/TheSimsSocial"},{"게임명":"플래티퍼스","평점":"0","장르":"어드벤처","한글 지원":"미지원","플랫폼":"PSN","가격":"패키지구매","개발사":"멈보 점보","유통사":"멈보 점보","일정":"[출시] 2009.11.17 (PSN)","사이트":""},{"게임명":"사이드 포켓 3","평점":"0","장르":"스포츠","한글 지원":"미지원","플랫폼":"PSN","가격":"패키지구매","개발사":"Hamster Corporation","유통사":"SCEI","일정":"[출시] 2009.11.20 (PSN)","사이트":""},{"게임명":"에피카 스텔라","평점":"0","장르":"RPG","한글 지원":"미지원","플랫폼":"PSN","가격":"패키지구매","개발사":"Hamster Corporation","유통사":"SCEI","일정":"[출시] 2009.11.20 (PSN)","사이트":""},{"게임명":"고대 7대 불가사의","평점":"0","장르":"퍼즐","한글 지원":"미지원","플랫폼":"PSN","가격":"패키지구매","개발사":"멈보 점보","유통사":"멈보 점보","일정":"[출시] 2009.11.17 (PSN)","사이트":""},{"게임명":"매든 NFL 아케이드","평점":"0","장르":"스포츠","한글 지원":"미지원","플랫폼":"PSN","가격":"패키지구매","개발사":"EA 스포츠","유통사":"EA 코리아","일정":"[출시] 2009.11.24 (PSN)","사이트":""}]