[{"게임명":"드래곤페이트","평점":"8","장르":"RPG","한글 지원":"미지원","플랫폼":"아이폰, 안드로이드","가격":"","개발사":"팜플","유통사":"","일정":"[CBT] 2015.02.25  클베는 안드만, 출시는 양쪽다 (안드로이드)[출시] 2015.05.08 (아이폰)[출시] 2015.03.26 (안드로이드)","사이트":""},{"게임명":"히어로즈 킹덤: 챔피언스 워","평점":"10","장르":"RPG, 액션","한글 지원":"미지원","플랫폼":"아이폰, 안드로이드","가격":"","개발사":"","유통사":"NHN엔터테인먼트","일정":"[CBT] 2015.02.11 (아이폰)[CBT] 2015.02.11 (안드로이드)[출시] 2015.05.29 (안드로이드)","사이트":""},{"게임명":"도쿄 스쿨 라이프","평점":"0","장르":"노벨, 어드벤처","한글 지원":"미지원","플랫폼":"PC","가격":"패키지구매","개발사":"M2","유통사":"","일정":"[출시] 2015.02.12 (PC)","사이트":""},{"게임명":"삼국전투기","평점":"0","장르":"RPG","한글 지원":"미지원","플랫폼":"안드로이드","가격":"부분유료화","개발사":"위레드소프트","유통사":"","일정":"[출시] 2015.02.16 (안드로이드)","사이트":""},{"게임명":"왕국사명","평점":"0","장르":"MMORPG","한글 지원":"미지원","플랫폼":"아이폰, 안드로이드","가격":"부분유료화","개발사":"에브리앱스","유통사":"","일정":"[출시] 2013.12.06 (아이폰)[출시] 2013.12.06 (안드로이드)[서비스종료] 2015.02.13 (아이폰)[서비스종료] 2015.02.13 (안드로이드)","사이트":""},{"게임명":"그림으로 말해요","평점":"0","장르":"퀴즈, 소셜","한글 지원":"미지원","플랫폼":"아이폰, 안드로이드","가격":"","개발사":"게임빌","유통사":"","일정":"[출시] 2011.08.24 (아이폰)[출시] 2011.08.24 (안드로이드)[출시] 2014.08.22 (안드로이드)[출시] 2015.03.15 (아이폰)","사이트":""},{"게임명":"드리프트 스피릿츠","평점":"0","장르":"레이싱","한글 지원":"미지원","플랫폼":"아이폰, 안드로이드","가격":"무료","개발사":"반다이남코 게임즈","유통사":"반다이남코 게임즈","일정":"[출시] 2013.11.06 (아이폰)[출시] 2014.05.29 (안드로이드)","사이트":"http://drispi.bngames.net/"},{"게임명":"작은 독재자","평점":"0","장르":"캐쥬얼","한글 지원":"미지원","플랫폼":"아이폰, 안드로이드","가격":"부분유료화","개발사":"빌트게임즈","유통사":"","일정":"[출시] 2015.02.12 (아이폰)[출시] 2015.02.12 (안드로이드)","사이트":""},{"게임명":"숙주나물인","평점":"8","장르":"캐쥬얼","한글 지원":"미지원","플랫폼":"아이폰, 안드로이드","가격":"무료","개발사":"굿드로이드","유통사":"","일정":"[출시] 2015.01.16 (아이폰)[출시] 2015.01.16 (안드로이드)","사이트":""},{"게임명":"맞짱미니골프 for Kakao","평점":"0","장르":"스포츠","한글 지원":"미지원","플랫폼":"안드로이드","가격":"부분유료화","개발사":"모코가","유통사":"","일정":"[출시] 2015.02.13 (안드로이드)[서비스종료] 2015.06.22 (안드로이드)","사이트":""}]