[{"게임명":"해피피쉬","평점":"0","장르":"소셜","한글 지원":"미지원","플랫폼":"아이폰, 안드로이드","가격":"부분유료화","개발사":"해피 엘리먼츠","유통사":"","일정":"[출시] 2012.12.04 (안드로이드)[출시] 2012.02.18 (아이폰)","사이트":""},{"게임명":"부자 용사!","평점":"0","장르":"액션","한글 지원":"미지원","플랫폼":"안드로이드","가격":"무료","개발사":"에이스송","유통사":"","일정":"[출시] 2015.04.09 (안드로이드)","사이트":""},{"게임명":"와리가리 치킨","평점":"0","장르":"가족","한글 지원":"미지원","플랫폼":"안드로이드","가격":"무료, 패키지구매","개발사":"게임테일즈","유통사":"","일정":"[출시] 2015.04.08  ios 심사중 (안드로이드)","사이트":""},{"게임명":"덕테일즈 리마스터드","평점":"0","장르":"액션","한글 지원":"미지원","플랫폼":"PC, PS3, Xbox360, 아이폰, WiiU, 안드로이드, 윈폰7","가격":"패키지구매","개발사":"","유통사":"캡콤","일정":"[출시] 2013.08.13 (PC)[출시] 2013.08.13 (PS3)[출시] 2013.08.13 (Xbox360)[출시] 2013.08.13 (아이폰)[출시] 2013.08.13 (안드로이드)[출시] 2013.08.13 (윈폰7)[출시] 2013.08.13 (WiiU)","사이트":""},{"게임명":"더 퀘스트 키퍼","평점":"0","장르":"어드벤처","한글 지원":"미지원","플랫폼":"아이폰, 안드로이드","가격":"부분유료화","개발사":"타이슨 이벨레","유통사":"","일정":"[출시] 2015.03.31 (아이폰)[출시] 2015.03.31 (안드로이드)","사이트":""},{"게임명":"천상비: 천의를 받드는 자","평점":"0","장르":"MORPG","한글 지원":"미지원","플랫폼":"안드로이드","가격":"부분유료화","개발사":"얼라이브 게임즈","유통사":"게임온 스튜디오","일정":"[서비스종료] 2015.09.04  서비스 종료 (안드로이드)","사이트":""},{"게임명":"요괴 워치 버스터즈 적묘단/백견대","평점":"7.5","장르":"RPG","한글 지원":"미지원","플랫폼":"3DS","가격":"패키지구매","개발사":"레벨 파이브","유통사":"","일정":"[출시] 2015.07.11 (3DS)[출시] 2018.04.19  한글판 (3DS)","사이트":""},{"게임명":"화신","평점":"0","장르":"MMORPG","한글 지원":"미지원","플랫폼":"웹브라우저","가격":"부분유료화","개발사":"광저우네트워크테크놀로지","유통사":"미디어웹","일정":"[출시] 2015.04.07 (웹브라우저)","사이트":"http://hs.game.daum.net/gate.html"},{"게임명":"타이탄 소울즈","평점":"0","장르":"어드벤처, 액션","한글 지원":"미지원","플랫폼":"PC, PSVITA, PS4","가격":"패키지구매","개발사":"애시드 너브","유통사":"디볼버 디지털","일정":"[출시] 2015.04.14 (PC)[출시] 2015.04.14 (PSVITA)[출시] 2015.04.14 (PS4)","사이트":""},{"게임명":"프로젝트 루트","평점":"0","장르":"슈팅, 액션","한글 지원":"미지원","플랫폼":"PC, PSVITA, PS4, XBOX ONE","가격":"패키지구매","개발사":"OPQAM","유통사":"키스","일정":"[출시] 2014.05.01 (PC)[출시] 2015.04.29 (PSVITA)[출시] 2015.04.29 (PS4)[출시] 2015.04.29 (XBOX ONE)","사이트":""}]