[{"게임명":"심콥터","평점":"0","장르":"비행, 시뮬레이션","한글 지원":"미지원","플랫폼":"PC","가격":"패키지구매","개발사":"맥시스","유통사":"EA 코리아","일정":"[출시] 1996.10.31 (PC)","사이트":""},{"게임명":"팝픈뮤직 12","평점":"0","장르":"뮤직","한글 지원":"미지원","플랫폼":"PS2","가격":"패키지구매","개발사":"코나미 컴퓨터 엔터테인먼트 재팬","유통사":"코나미","일정":"[출시] 2006.03.02 (PS2)","사이트":"http://www.konami.jp/bemani/popn/gs/12/"},{"게임명":"지오닉프론트-기동전사건담0079","평점":"0","장르":"전략","한글 지원":"미지원","플랫폼":"PS2","가격":"패키지구매","개발사":"반다이","유통사":"반다이","일정":"[출시] 2001.07.01 (PS2)","사이트":"http://www.gundam.channel.or.jp/"},{"게임명":"삼국지 3","평점":"0","장르":"전략, 시뮬레이션","한글 지원":"미지원","플랫폼":"PC","가격":"패키지구매","개발사":"코에이테크모","유통사":"코에이테크모","일정":"[출시] 1992.11.08 (PC)","사이트":"http://www.gamecity.ne.jp/products/products/ee/Rlsan3.htm"},{"게임명":"태고의 달인 고! 고! 5대목","평점":"0","장르":"뮤직","한글 지원":"미지원","플랫폼":"PS2","가격":"패키지구매","개발사":"반다이남코 게임즈","유통사":"SCE","일정":"[출시] 2003.10.05 (PS2)","사이트":"http://taiko.namco-ch.net/"},{"게임명":"메가레이스 2","평점":"0","장르":"레이싱","한글 지원":"미지원","플랫폼":"PC","가격":"패키지구매","개발사":"크리요","유통사":"마인드스케이프","일정":"[출시] 1996.01.01 (PC)","사이트":""},{"게임명":"태고의 달인 애니메스페셜","평점":"0","장르":"뮤직","한글 지원":"미지원","플랫폼":"PS2","가격":"패키지구매","개발사":"반다이남코 게임즈","유통사":"SCE","일정":"[출시] 2004.03.25 (PS2)","사이트":"http://taiko.namco-ch.net/"},{"게임명":"태고의 달인 4대목 : 모여라 축제다!","평점":"0","장르":"뮤직","한글 지원":"미지원","플랫폼":"PS2","가격":"패키지구매","개발사":"반다이남코 게임즈","유통사":"SCE","일정":"[출시] 2002.12.16 (PS2)","사이트":"http://taiko.namco-ch.net/"},{"게임명":"제로의 사역마 : 미아의 종지부와 기천의 교향곡","평점":"0","장르":"어드벤처","한글 지원":"미지원","플랫폼":"PS2","가격":"패키지구매","개발사":"마벨러스 인터렉티브","유통사":"마벨러스 인터렉티브","일정":"[출시] 2008.10.18 (PS2)","사이트":"http://www.mmv.co.jp/special/game/ps2/zero3/"},{"게임명":"듄 2000","평점":"0","장르":"RTS","한글 지원":"미지원","플랫폼":"PC","가격":"패키지구매","개발사":"웨스트우드","유통사":"버진","일정":"[출시] 1998.09.01 (PC)","사이트":""}]