[{"게임명":"드래곤즈 도그마: 다크 어리즌","평점":"8","장르":"액션","한글 지원":"미지원","플랫폼":"PC, PS3, Xbox360, PS4, XBOX ONE, SWITCH","가격":"패키지구매","개발사":"캡콤","유통사":"게임피아","일정":"[출시] 2013.04.25 (PS3)[출시] 2013.04.25 (Xbox360)[출시] 2016.01.16 (PC)[출시] 2017.10.02 (PS4)[출시] 2017.10.02 (XBOX ONE)[출시] 2019.04.25 (SWITCH)","사이트":""},{"게임명":"천행검","평점":"0","장르":"웹, MMORPG","한글 지원":"미지원","플랫폼":"웹브라우저","가격":"부분유료화","개발사":"(주)와이제이 네트워크 코리아","유통사":"(주)와이제이 네트워크 코리아","일정":"[서비스종료] 2015.03.26 (웹브라우저)","사이트":""},{"게임명":"디즈니 파티하우스 for Kakao","평점":"0","장르":"퍼즐","한글 지원":"미지원","플랫폼":"아이폰, 안드로이드","가격":"부분유료화","개발사":"인크레더블스튜디오","유통사":"인크레더블스튜디오","일정":"[출시] 2013.04.16 (아이폰)[출시] 2013.04.16 (안드로이드)","사이트":""},{"게임명":"미니기어즈 for Kakao","평점":"0","장르":"슈팅","한글 지원":"미지원","플랫폼":"아이폰, 안드로이드","가격":"부분유료화","개발사":"액토즈 소프트","유통사":"액토즈 소프트","일정":"[출시] 2013.04.16 (아이폰)[출시] 2013.04.16 (안드로이드)[서비스종료] 2015.02.27 (아이폰)[서비스종료] 2015.02.27 (안드로이드)","사이트":""},{"게임명":"미니모터레이싱 for Kakao","평점":"0","장르":"레이싱","한글 지원":"미지원","플랫폼":"아이폰, 안드로이드","가격":"부분유료화","개발사":"셀바스","유통사":"셀바스","일정":"[출시] 2013.04.16 (아이폰)[출시] 2013.04.16 (안드로이드)","사이트":"http://www.selvas.com/games/detail.aspx?number=122&page=1&tab=1&soon_in=All&category_in=&keyword_in="},{"게임명":"에어헌터 for Kakao","평점":"8","장르":"슈팅","한글 지원":"미지원","플랫폼":"아이폰, 안드로이드","가격":"부분유료화","개발사":"위메이드 엔터테인먼트","유통사":"위메이드 엔터테인먼트","일정":"[출시] 2013.04.16 (아이폰)[출시] 2013.04.16 (안드로이드)","사이트":"http://weme.wemade.com/game/game_info.asp?GmCode=27"},{"게임명":"매일매일 스도쿠 for Kakao","평점":"0","장르":"퍼즐","한글 지원":"미지원","플랫폼":"아이폰, 안드로이드","가격":"부분유료화","개발사":"위메이드 엔터테인먼트","유통사":"위메이드 엔터테인먼트","일정":"[서비스중단] 2014.00.00 (아이폰)[서비스중단] 2014.00.00 (안드로이드)","사이트":""},{"게임명":"인저스티스: 갓 어몽 어스","평점":"2.8","장르":"격투","한글 지원":"미지원","플랫폼":"PC, PS3, Xbox360, WiiU, PSVITA, PS4","가격":"패키지구매","개발사":"네더렐름스튜디오","유통사":"워너브라더스","일정":"[출시] 2013.04.16 (PS3)[출시] 2013.04.16 (Xbox360)[출시] 2013.04.16 (WiiU)[출시] 2013.11.15 (PS4)[출시] 2013.04.16 (PC)[출시] 2013.04.16 (PSVITA)","사이트":"http://www.injustice.com/en"},{"게임명":"마리오 테니스","평점":"9.2","장르":"스포츠","한글 지원":"한국어지원(자막)","플랫폼":"3DS","가격":"패키지구매","개발사":"","유통사":"","일정":"[출시] 2013.04.18 (3DS)","사이트":""},{"게임명":"세븐 드래곤 2020-2","평점":"7","장르":"RPG","한글 지원":"미지원","플랫폼":"PSP","가격":"패키지구매","개발사":"","유통사":"","일정":"[출시] 2013.04.18 (PSP)","사이트":""}]