[{"게임명":"그란투리스모 2","평점":"0","장르":"레이싱","한글 지원":"미지원","플랫폼":"PS","가격":"패키지구매","개발사":"폴리포니 디지털","유통사":"SCEJ","일정":"[출시] 1999.12.11 (PS)","사이트":""},{"게임명":"스트리트 파이터 3: 더블 임팩트","평점":"0","장르":"격투, 액션","한글 지원":"미지원","플랫폼":"DC, AC","가격":"패키지구매","개발사":"캡콤","유통사":"캡콤","일정":"[출시] 1999.12.16 (DC)","사이트":""},{"게임명":"스타크래프트 64","평점":"0","장르":"RTS","한글 지원":"미지원","플랫폼":"N64","가격":"기타","개발사":"블리자드","유통사":"닌텐도","일정":"[출시] 2000.06.01 (N64)","사이트":""},{"게임명":"리바이브: 소생","평점":"0","장르":"육성, 시뮬레이션","한글 지원":"미지원","플랫폼":"DC","가격":"","개발사":"데이터이스트","유통사":"데이터이스트","일정":"[출시] 1999.10.01 (DC)","사이트":""},{"게임명":"마블 VS 캡콤 크래시 오브 슈퍼 히어로즈","평점":"0","장르":"격투, 액션","한글 지원":"미지원","플랫폼":"PS, DC, AC","가격":"패키지구매","개발사":"캡콤","유통사":"캡콤","일정":"[출시] 1999.11.11 (PS)[출시] 1998.01.12 (AC)[출시] 1999.03.25 (DC)","사이트":""},{"게임명":"로빈 로이드의 모험","평점":"0","장르":"어드벤처","한글 지원":"미지원","플랫폼":"PS3, PSN, PS, PSP","가격":"기타","개발사":"거스트","유통사":"거스트","일정":"[출시] 2008.10.01 (PS3)[출시] 2008.10.01 (PS)[출시] 2008.10.01 (PSP)[출시] 2008.10.23 (PSN)","사이트":""},{"게임명":"댄싱 스테이지 피튜어링 트루키스 데스티네이션(TDK)","평점":"0","장르":"리듬, 액션","한글 지원":"미지원","플랫폼":"PS","가격":"기타","개발사":"코나미 재팬","유통사":"코나미 재팬","일정":"[출시] 2000.04.20 (PS)","사이트":""},{"게임명":"파워스매쉬","평점":"0","장르":"스포츠","한글 지원":"미지원","플랫폼":"DC, AC","가격":"패키지구매","개발사":"세가","유통사":"세가","일정":"[출시] 2001.07.01 (AC)[출시] 2001.07.01 (DC)","사이트":""},{"게임명":"B비더맨 폭 외전Ⅵ ∼파이널 메가튠","평점":"0","장르":"노벨","한글 지원":"미지원","플랫폼":"GBC","가격":"기타","개발사":"미디어 팩토리","유통사":"미디어 팩토리","일정":"[출시] 2000.01.01 (GBC)","사이트":""},{"게임명":"사쿠라 대전GB: 격 하나구미 입대!","평점":"0","장르":"어드벤처","한글 지원":"미지원","플랫폼":"GBA","가격":"패키지구매","개발사":"세가","유통사":"세가","일정":"[출시] 2000.07.27 (GP32)","사이트":"http://sakura-taisen.com/"}]