[{"게임명":"드로운 투 데스","평점":"4.5","장르":"TPS","한글 지원":"한국어지원(자막)","플랫폼":"PS4","가격":"패키지구매","개발사":"SIE 샌디에고 스튜디오","유통사":"SIEK","일정":"[출시] 2017.04.04  한글판 (PS4)","사이트":""},{"게임명":"갓 워즈: 시대를 넘어","평점":"6","장르":"SRPG","한글 지원":"한국어지원(자막)","플랫폼":"PSVITA, PS4, SWITCH","가격":"패키지구매","개발사":"카도가와 게임즈","유통사":"신세계I&C","일정":"[출시] 2017.06.20 (PS4)[출시] 2017.06.20 (PSVITA)","사이트":""},{"게임명":"모탈 블리츠","평점":"0","장르":"VR, FPS","한글 지원":"한국어지원(음성/자막)","플랫폼":"PS4","가격":"패키지구매","개발사":"스코넥엔터테인먼트","유통사":"","일정":"[출시] 2017.04.04 (PS4)","사이트":""},{"게임명":"유카-레일리","평점":"10","장르":"어드벤처","한글 지원":"미지원","플랫폼":"PC, PS4, XBOX ONE, SWITCH","가격":"패키지구매","개발사":"플레이토닉 게임즈","유통사":"","일정":"[출시] 2017.04.11  북미 (PC)[출시] 2017.04.11  북미 (PS4)[출시] 2017.04.11  북미 (XBOX ONE)[출시] 2017.00.00 (SWITCH)[출시] 2017.12.12  한글판 (PS4)","사이트":""},{"게임명":"플랫아웃 4","평점":"0","장르":"레이싱","한글 지원":"한국어지원(자막)","플랫폼":"PC, PS4, XBOX ONE","가격":"패키지구매","개발사":"Kylotonn","유통사":"빅벤 인터렉티브","일정":"[출시] 2017.03.17  북미 (PS4)[출시] 2017.03.17  북미 (XBOX ONE)[출시] 2017.04.04 (PC)[출시] 2017.08.01  한글판 (PS4)[출시] 2017.08.01  한글판 (PC)","사이트":""},{"게임명":"스타블러드 아레나","평점":"0","장르":"액션","한글 지원":"미지원","플랫폼":"PS4","가격":"패키지구매","개발사":"화이트문 드림스","유통사":"SIE","일정":"[출시] 2017.04.11  북미 (PS4)","사이트":"https://starbloodarena.com/en-us/home"},{"게임명":"파이어 엠블렘: 에코즈","평점":"9.5","장르":"SRPG","한글 지원":"한국어지원(자막)","플랫폼":"3DS","가격":"패키지구매","개발사":"닌텐도","유통사":"한국 닌텐도","일정":"[출시] 2017.04.20  일본 (3DS)[출시] 2017.07.13  한글판 (3DS)","사이트":"https://www.nintendo.co.jp/3ds/ajjj/index.html"},{"게임명":"프로야구 패미스타 클라이맥스","평점":"0","장르":"스포츠","한글 지원":"미지원","플랫폼":"3DS","가격":"패키지구매","개발사":"반다이 남코 엔터테인먼트","유통사":"","일정":"[출시] 2017.04.20  일본 (3DS)","사이트":"http://2017.famista.jp/"},{"게임명":"던전 트래블러즈 2-2 타락한 소녀와 시작의 서","평점":"7.5","장르":"RPG","한글 지원":"미지원","플랫폼":"PSVITA","가격":"패키지구매","개발사":"아쿠아 플러스","유통사":"","일정":"[출시] 2017.04.20  일본 (PSVITA)","사이트":"http://aquaplus.jp/dt2-2/"},{"게임명":"펜타스톰 for Kakao","평점":"0","장르":"AOS","한글 지원":"한국어지원(음성/자막)","플랫폼":"아이폰, 안드로이드","가격":"부분유료화","개발사":"넷마블 게임즈","유통사":"","일정":"[OBT] 2017.04.07  프리미엄 사전 테스트 (안드로이드)","사이트":""}]