[{"게임명":"데빌 메이 크라이: 디피니티브 에디션","평점":"0","장르":"액션","한글 지원":"미지원","플랫폼":"PS4, XBOX ONE","가격":"패키지구매","개발사":"닌자 씨어리","유통사":"캡콤","일정":"[출시] 2015.03.10 (PS4)[출시] 2015.03.10 (XBOX ONE)","사이트":""},{"게임명":"판타지 디펜더스 2","평점":"0","장르":"디펜스","한글 지원":"미지원","플랫폼":"안드로이드","가격":"부분유료화","개발사":"에쎈모바일","유통사":"NHN 한게임","일정":"[출시] 2013.06.04 (안드로이드)[서비스종료] 2015.04.02 (안드로이드)","사이트":""},{"게임명":"블러드&글로리: 불멸","평점":"0","장르":"RPG, 액션","한글 지원":"미지원","플랫폼":"아이폰, 안드로이드","가격":"부분유료화","개발사":"글루 모바일","유통사":"","일정":"[출시] 2015.03.04 (아이폰)[출시] 2015.03.04 (안드로이드)","사이트":""},{"게임명":"캔디 크러쉬 소다","평점":"7","장르":"캐쥬얼, 퍼즐","한글 지원":"미지원","플랫폼":"아이폰, 안드로이드","가격":"부분유료화","개발사":"킹닷컴","유통사":"","일정":"[출시] 2015.03.05 (아이폰)[출시] 2015.03.05 (안드로이드)","사이트":""},{"게임명":"외계소년아우터","평점":"0","장르":"RPG","한글 지원":"미지원","플랫폼":"안드로이드","가격":"부분유료화, 패키지구매","개발사":"영우게임즈","유통사":"","일정":"[출시] 2015.01.01  z버전(유료)는 2/5 (안드로이드)","사이트":""},{"게임명":"트라인 인챈티드 에디션","평점":"7","장르":"액션","한글 지원":"미지원","플랫폼":"PC, WiiU, PS4","가격":"패키지구매","개발사":"프로즌바이튼","유통사":"","일정":"[출시] 2015.03.05 (PS4)[출시] 2009.07.02 (PC)[출시] 2015.03.12 (WiiU)","사이트":""},{"게임명":"쉘 위 데이트? 닌자의유혹+","평점":"0","장르":"연애, 시뮬레이션","한글 지원":"미지원","플랫폼":"아이폰, 안드로이드","가격":"부분유료화","개발사":"","유통사":"엔티티 솔마레","일정":"[출시] 2014.02.23 (아이폰)[출시] 2014.02.23 (안드로이드)","사이트":""},{"게임명":"소닉 러너즈","평점":"0","장르":"캐쥬얼, 액션","한글 지원":"미지원","플랫폼":"아이폰, 안드로이드","가격":"","개발사":"소닉 팀","유통사":"세가네트웍스","일정":"[출시] 2015.02.25  일본/캐나다 (아이폰)[출시] 2015.02.25  일본/캐나다 (안드로이드)","사이트":""},{"게임명":"스타스트라이크 울트라","평점":"8.8","장르":"슈팅","한글 지원":"한국어지원(자막)","플랫폼":"PS4","가격":"패키지구매","개발사":"","유통사":"","일정":"[출시] 2015.03.05 (PS4)","사이트":""},{"게임명":"헬다이버스","평점":"9.1","장르":"TPS","한글 지원":"한국어지원(자막)","플랫폼":"PS3, PSN, PSVITA, PS4","가격":"","개발사":"에로우헤드 게임 스튜디오","유통사":"SCEA","일정":"[출시] 2015.03.05 (PS3)[출시] 2015.03.05 (PSVITA)[출시] 2015.03.05 (PS4)","사이트":""}]