[{"게임명":"짱구는 못말려 for Kakao","평점":"0","장르":"액션","한글 지원":"미지원","플랫폼":"안드로이드","가격":"부분유료화","개발사":"","유통사":"(주)구미","일정":"[서비스종료] 2015.01.27 (안드로이드)","사이트":""},{"게임명":"미니워리어스 For Kakao","평점":"0","장르":"전략, 시뮬레이션","한글 지원":"미지원","플랫폼":"안드로이드","가격":"부분유료화","개발사":"트리니티 인터액티브","유통사":"","일정":"[출시] 2015.01.27 (안드로이드)","사이트":""},{"게임명":"허니쟁 for Kakao","평점":"0","장르":"RPG","한글 지원":"미지원","플랫폼":"아이폰, 안드로이드","가격":"부분유료화","개발사":"","유통사":"디앱스게임즈","일정":"[출시] 2015.01.27 (안드로이드)[출시] 2015.06.16 (아이폰)","사이트":""},{"게임명":"모두의쿠키 for Kakao","평점":"10","장르":"퍼즐","한글 지원":"미지원","플랫폼":"아이폰, 안드로이드","가격":"부분유료화","개발사":"넷마블","유통사":"","일정":"[출시] 2015.01.27 (아이폰)[출시] 2015.01.27 (안드로이드)","사이트":""},{"게임명":"협객 온라인","평점":"0","장르":"MMORPG","한글 지원":"미지원","플랫폼":"온라인","가격":"부분유료화","개발사":"(주)마누","유통사":"","일정":"[미정] 0000.00.00 (온라인)","사이트":""},{"게임명":"홈월드 리마스터드 콜렉션","평점":"0","장르":"전략, 시뮬레이션","한글 지원":"미지원","플랫폼":"PC","가격":"패키지구매","개발사":"기어박스","유통사":"","일정":"[출시] 2015.02.25 (PC)","사이트":"http://www.homeworldremastered.com/"},{"게임명":"라인 레인저스","평점":"10","장르":"디펜스","한글 지원":"미지원","플랫폼":"아이폰, 안드로이드","가격":"부분유료화","개발사":"라인","유통사":"","일정":"[출시] 2014.03.03 (아이폰)[출시] 2014.03.03 (안드로이드)","사이트":""},{"게임명":"크림슨하트 2  for kakao","평점":"0","장르":"RPG","한글 지원":"미지원","플랫폼":"아이폰, 안드로이드","가격":"부분유료화","개발사":"에이앤비소프트","유통사":"","일정":"[출시] 2013.08.27 (아이폰)[출시] 2013.08.27 (안드로이드)[서비스종료] 2015.02.23 (아이폰)[서비스종료] 2015.02.23 (안드로이드)","사이트":""},{"게임명":"우주전쟁 TD","평점":"0","장르":"디펜스, 액션","한글 지원":"미지원","플랫폼":"아이폰, 안드로이드","가격":"부분유료화","개발사":"폴리큐브","유통사":"","일정":"[출시] 2013.01.27 (아이폰)[출시] 2015.01.22 (안드로이드)","사이트":""},{"게임명":"괴인럼블","평점":"0","장르":"카드","한글 지원":"미지원","플랫폼":"아이폰, 안드로이드","가격":"부분유료화","개발사":"플레이어스","유통사":"게임빌","일정":"[출시] 2013.08.20 (안드로이드)[출시] 2013.11.12 (아이폰)[서비스종료] 2015.02.24 (아이폰)[서비스종료] 2015.02.24 (안드로이드)","사이트":""}]