[{"게임명":"다이로쿠 아야카시모리","평점":"0","장르":"어드벤처","한글 지원":"미지원","플랫폼":"SWITCH","가격":"패키지구매","개발사":"아이디어 팩토리","유통사":"","일정":"[출시] 2020.05.28 (SWITCH)","사이트":""},{"게임명":"커맨드 앤 컨커 리마스터드 콜렉션","평점":"10","장르":"RTS","한글 지원":"미지원","플랫폼":"PC","가격":"패키지구매","개발사":"페트로글리프 게임즈","유통사":"","일정":"[출시] 2020.06.06 (PC)","사이트":""},{"게임명":"아세토 코르사  컴페티치오네","평점":"0","장르":"레이싱","한글 지원":"한국어지원(자막)","플랫폼":"PC, PS4, XBOX ONE","가격":"패키지구매","개발사":"쿠노스 시뮬라지오니","유통사":"","일정":"[출시] 2019.05.29 (PC)[출시] 2019.05.29 (PS4)[출시] 2019.05.29 (XBOX ONE)[출시] 2020.06.23  한국 정발 (PS4)","사이트":""},{"게임명":"데스페라도스 3","평점":"8.3","장르":"전략","한글 지원":"한국어지원(자막)","플랫폼":"PC, PS4, XBOX ONE","가격":"패키지구매","개발사":"미미미 프로덕션","유통사":"","일정":"[출시] 2020.06.17 (PC)[출시] 2020.06.17 (PS4)[출시] 2020.06.17 (XBOX ONE)[출시] 2020.07.01  한국 정발 (PS4)","사이트":""},{"게임명":"디스인테그레이션","평점":"5","장르":"FPS","한글 지원":"한국어지원(자막)","플랫폼":"PC, PS4, XBOX ONE","가격":"패키지구매","개발사":"프라이빗 디비전, V1 인터랙티브","유통사":"","일정":"[출시] 2020.06.16 (PC)[출시] 2020.06.16 (PS4)[출시] 2020.06.16 (XBOX ONE)","사이트":""},{"게임명":"카트라이더 러쉬플러스","평점":"0","장르":"레이싱","한글 지원":"한국어지원(음성/자막)","플랫폼":"아이폰, 안드로이드","가격":"부분유료화","개발사":"㈜넥슨 코리아","유통사":"","일정":"[출시] 2019.07.02  중국 (아이폰)[출시] 2019.07.02  중국 (안드로이드)[출시] 2020.05.12  한국 (아이폰)[출시] 2020.05.12  한국 (안드로이드)","사이트":""},{"게임명":"헬테이커","평점":"0","장르":"퍼즐, 어드벤처","한글 지원":"미지원","플랫폼":"PC","가격":"부분유료화","개발사":"","유통사":"","일정":"[출시] 2020.05.11 (PC)","사이트":""},{"게임명":"일루전 커넥트","평점":"0","장르":"TCG, 카드","한글 지원":"미지원","플랫폼":"아이폰, 안드로이드","가격":"부분유료화","개발사":"드래곤펀치스톰 (DP 스톰)","유통사":"창유","일정":"[출시] 2020.02.26  대만/홍콩/마카오 (아이폰)[출시] 2020.02.26  대만/홍콩/마카오 (안드로이드)[출시] 2020.04.07  중국 (아이폰)[출시] 2020.04.07  중국 (안드로이드)[출시] 2020.09.10  한국 (아이폰)[출시] 2020.09.10  한국 (안드로이드)","사이트":"http://changyou.co.kr/illusion_connect/"},{"게임명":"카트라이더: 드리프트","평점":"0","장르":"레이싱","한글 지원":"미지원","플랫폼":"PC, XBOX ONE","가격":"부분유료화","개발사":"㈜넥슨 코리아","유통사":"","일정":"[CBT] 2020.06.04 (PC)[CBT] 2020.06.04 (XBOX ONE)","사이트":""},{"게임명":"폴아웃 쉘터 Online","평점":"0","장르":"시뮬레이션","한글 지원":"한국어지원(자막)","플랫폼":"아이폰, 안드로이드","가격":"부분유료화","개발사":"Shengqu Games","유통사":"","일정":"[출시] 2020.06.01 (아이폰)[출시] 2020.06.01 (안드로이드)","사이트":""}]