[{"게임명":"여신의 기사단","평점":"10","장르":"액션","한글 지원":"미지원","플랫폼":"안드로이드","가격":"부분유료화","개발사":"4399","유통사":"","일정":"[출시] 2014.10.10  구글/티스토어/네이버 (안드로이드)","사이트":""},{"게임명":"구석살이: 여기가 편해요","평점":"0","장르":"기타","한글 지원":"미지원","플랫폼":"3DS","가격":"패키지구매","개발사":"콜롬비아 게임즈","유통사":"","일정":"[출시] 2014.11.20 (3DS)","사이트":"http://www.columbia-games.com/3ds/sumikko/"},{"게임명":"팀 인디","평점":"0","장르":"액션","한글 지원":"미지원","플랫폼":"PC","가격":"패키지구매","개발사":"브라이트사이드 게임즈","유통사":"","일정":"[출시] 2014.10.08 (PC)","사이트":"http://teamindie.brightside-games.com/"},{"게임명":"드래곤 퀘스트 빌더즈","평점":"7.9","장르":"RPG","한글 지원":"미지원","플랫폼":"PS3, PSVITA, PS4, SWITCH","가격":"패키지구매","개발사":"스퀘어 에닉스","유통사":"","일정":"[출시] 2016.01.28  일본 (PS3)[출시] 2016.01.28  일본 (PSVITA)[출시] 2016.01.28  일본 (PS4)[출시] 2016.04.28  한글판 (PSVITA)[출시] 2016.04.28  한글판 (PS4)[출시] 2018.02.09 (SWITCH)","사이트":"http://www.dragonquest.jp/builders/"},{"게임명":"카: 번개처럼 달려라","평점":"0","장르":"레이싱","한글 지원":"미지원","플랫폼":"아이폰, 안드로이드","가격":"부분유료화","개발사":"게임로프트","유통사":"","일정":"[출시] 2014.10.10 (아이폰)[출시] 2014.10.10 (안드로이드)","사이트":""},{"게임명":"핑거파이어 for Kakao","평점":"0","장르":"퍼즐","한글 지원":"미지원","플랫폼":"안드로이드","가격":"부분유료화","개발사":"주식회사클라우드세븐","유통사":"","일정":"[출시] 2014.10.10  for kakao 기준 출시일 (안드로이드)","사이트":""},{"게임명":"재기드 얼라이언스 플래시백","평점":"0","장르":"전략, RPG","한글 지원":"미지원","플랫폼":"PC","가격":"패키지구매","개발사":"풀 컨트롤","유통사":"","일정":"[출시] 2014.10.21 (PC)","사이트":""},{"게임명":"전진! 키노피오 대장","평점":"9.5","장르":"퍼즐, 전략","한글 지원":"미지원","플랫폼":"WiiU, 3DS, SWITCH","가격":"패키지구매","개발사":"닌텐도","유통사":"","일정":"[출시] 2014.11.13  일본발매 (WiiU)[출시] 2018.07.13 (SWITCH)[출시] 2018.07.13 (3DS)","사이트":""},{"게임명":"엘","평점":"0","장르":"액션","한글 지원":"미지원","플랫폼":"아이폰, 안드로이드","가격":"무료","개발사":"그리","유통사":"","일정":"[출시] 2014.09.13 (아이폰)[출시] 2014.09.13 (안드로이드)","사이트":""},{"게임명":"게임 오브 워 - 파이어 에이지 for Kakao","평점":"0","장르":"전략","한글 지원":"미지원","플랫폼":"아이폰, 안드로이드","가격":"부분유료화","개발사":"머신존","유통사":"","일정":"[출시] 2014.10.07 (아이폰)[출시] 2014.05.10 (안드로이드)","사이트":""}]