[{"게임명":"리니지","평점":"6.3","장르":"MMORPG","한글 지원":"미지원","플랫폼":"온라인","가격":"정액제","개발사":"엔씨소프트","유통사":"엔씨소프트","일정":"[출시] 1998.00.00 (온라인)","사이트":"http://lineage.plaync.co.kr/"},{"게임명":"조선협객전","평점":"0","장르":"MMORPG","한글 지원":"미지원","플랫폼":"온라인","가격":"부분유료화","개발사":"본 게임","유통사":"본 게임","일정":"[OBT] 2007.09.07 (온라인)","사이트":"http://www.borngame.com/"},{"게임명":"비트댄스","평점":"0","장르":"리듬, 액션","한글 지원":"미지원","플랫폼":"온라인","가격":"기타","개발사":"㈜넥슨","유통사":"㈜넥슨","일정":"[서비스종료] 2002.00.00 (온라인)","사이트":""},{"게임명":"사이버 월드컵","평점":"0","장르":"스포츠","한글 지원":"미지원","플랫폼":"온라인","가격":"기타","개발사":"아담소프트","유통사":"아담소프트","일정":"[서비스중단] 2000.05.13 (온라인)","사이트":""},{"게임명":"캐롬 3D 온라인 당구","평점":"0","장르":"스포츠","한글 지원":"미지원","플랫폼":"온라인","가격":"부분유료화","개발사":"네오액트","유통사":"아스트로네스트","일정":"[출시] 2000.04.01 (온라인)[서비스중단] 2011.10.21 (온라인)","사이트":""},{"게임명":"아크메이지: 마테르","평점":"0","장르":"MMORPG","한글 지원":"미지원","플랫폼":"온라인","가격":"기타","개발사":"마리텔레콤","유통사":"마리텔레콤","일정":"[출시] 1999.00.00 (온라인)","사이트":""},{"게임명":"강철제국 온라인","평점":"0","장르":"웹","한글 지원":"미지원","플랫폼":"온라인","가격":"기타","개발사":"손노리","유통사":"위자드 소프트","일정":"[서비스종료] 2000.00.00 (온라인)","사이트":""},{"게임명":"유레스","평점":"7.5","장르":"MMORPG","한글 지원":"미지원","플랫폼":"온라인","가격":"기타","개발사":"NAS정보기술","유통사":"NAS정보기술","일정":"[서비스종료] 2004.00.00 (온라인)","사이트":""},{"게임명":"미르의 전설 2","평점":"0","장르":"MMORPG","한글 지원":"미지원","플랫폼":"온라인","가격":"부분유료화","개발사":"위메이드 엔터테인먼트","유통사":"와이디온라인","일정":"[출시] 2001.03.21 (온라인)","사이트":"http://mir2.wemade.com/"},{"게임명":"가디우스","평점":"0","장르":"MMORPG","한글 지원":"미지원","플랫폼":"온라인","가격":"기타","개발사":"이스트 엔터테인먼트","유통사":"이스트 엔터테인먼트","일정":"[서비스중단] 2007.00.00 (온라인)","사이트":""}]