[{"게임명":"하프라이프","평점":"0","장르":"FPS","한글 지원":"미지원","플랫폼":"PC","가격":"패키지구매","개발사":"밸브 소프트웨어","유통사":"씨디빌","일정":"[출시] 1998.11.01 (PC)","사이트":"http://orange.half-life2.com/"},{"게임명":"세븐 킹덤스","평점":"0","장르":"RTS","한글 지원":"미지원","플랫폼":"PC","가격":"기타","개발사":"인라이트 소프트웨어","유통사":"웅진미디어","일정":"[출시] 1997.11.01 (PC)","사이트":""},{"게임명":"잃어버린 제국","평점":"0","장르":"전략, 시뮬레이션","한글 지원":"미지원","플랫폼":"PC","가격":"패키지구매","개발사":"마티즈 게임소프트웨어","유통사":"MCB소프트","일정":"[출시] 2000.01.01 (PC)","사이트":""},{"게임명":"임진록","평점":"0","장르":"RTS","한글 지원":"미지원","플랫폼":"PC","가격":"기타","개발사":"HQ team","유통사":"삼성전자","일정":"[출시] 1997.01.01 (PC)","사이트":""},{"게임명":"하프라이프: 어포징 포스","평점":"0","장르":"FPS","한글 지원":"미지원","플랫폼":"PC","가격":"패키지구매","개발사":"기어박스","유통사":"씨디빌","일정":"[출시] 2000.01.12 (PC)","사이트":""},{"게임명":"세븐 킹덤스2","평점":"0","장르":"RTS","한글 지원":"미지원","플랫폼":"PC","가격":"기타","개발사":"인라이트 소프트웨어","유통사":"티쓰리엔터테인먼트","일정":"[출시] 1999.07.01 (PC)","사이트":"http://www.enlight.com/7k2/"},{"게임명":"녹스","평점":"8","장르":"RPG","한글 지원":"미지원","플랫폼":"PC","가격":"패키지구매","개발사":"웨스트우드","유통사":"EA 코리아","일정":"[출시] 2000.01.01 (PC)","사이트":""},{"게임명":"헤비기어","평점":"0","장르":"비행, 시뮬레이션","한글 지원":"미지원","플랫폼":"PC","가격":"패키지구매","개발사":"액티비전","유통사":"액티비전","일정":"[출시] 1997.10.01 (PC)","사이트":""},{"게임명":"세인트 아이즈","평점":"0","장르":"RPG","한글 지원":"미지원","플랫폼":"PC","가격":"패키지구매","개발사":"TGL","유통사":"비오비소프트","일정":"[출시] 1999.00.00 (PC)","사이트":""},{"게임명":"헤비기어 2","평점":"0","장르":"액션","한글 지원":"미지원","플랫폼":"PC","가격":"패키지구매","개발사":"액티비전","유통사":"위자드 소프트","일정":"[출시] 1999.05.01 (PC)","사이트":""}]