[{"게임명":"광개토대왕","평점":"0","장르":"RPG","한글 지원":"미지원","플랫폼":"PC","가격":"패키지구매","개발사":"동서게임채널","유통사":"동서게임채널","일정":"[출시] 1995.00.00 (PC)","사이트":""},{"게임명":"디사이플스 3: 르네상스","평점":"0","장르":"전략","한글 지원":"미지원","플랫폼":"PC","가격":"패키지구매","개발사":"아켈라","유통사":"칼립소미디어","일정":"[출시] 2010.07.13 (PC)","사이트":"http://en.akella.com/Game.aspx?id=28"},{"게임명":"영원의 아세리아: 이 대지의 끝에서","평점":"0","장르":"SRPG","한글 지원":"미지원","플랫폼":"PSP","가격":"패키지구매","개발사":"사이버프론트(주)","유통사":"사이버프론트(주)","일정":"[출시] 2012.03.08 (PSP)","사이트":""},{"게임명":"걸즈 RPG: 신데렐라이프","평점":"0","장르":"RPG","한글 지원":"미지원","플랫폼":"3DS","가격":"패키지구매","개발사":"5 레벨","유통사":"5 레벨","일정":"[출시] 2012.03.08 (3DS)","사이트":"http://www.cinderelife.jp/index.html"},{"게임명":"포켓몬+노부나가의 야망","평점":"9","장르":"시뮬레이션","한글 지원":"미지원","플랫폼":"NDS","가격":"패키지구매","개발사":"게임프릭","유통사":"포켓몬","일정":"[출시] 2012.03.17 (NDS)","사이트":""},{"게임명":"여자아이와 밀실에 있으면 ㅇㅇ할지도 몰라","평점":"0","장르":"어드벤처","한글 지원":"미지원","플랫폼":"3DS","가격":"패키지구매","개발사":"D3 퍼블리셔","유통사":"D3 퍼블리셔","일정":"[출시] 2012.03.15 (3DS)","사이트":""},{"게임명":"샤이닝 블레이드","평점":"6","장르":"RPG, 액션","한글 지원":"미지원","플랫폼":"PSP","가격":"패키지구매","개발사":"세가","유통사":"세가","일정":"[출시] 2012.03.15 (PSP)","사이트":"http://shining-world.jp/blade/"},{"게임명":"마법소녀 마도카 마기카 포터블","평점":"5.8","장르":"RPG","한글 지원":"미지원","플랫폼":"PSP","가격":"패키지구매","개발사":"니트로 플러스","유통사":"반다이남코 게임즈","일정":"[출시] 2012.03.15 (PSP)","사이트":""},{"게임명":"엑스컴: UFO 디펜스","평점":"0","장르":"전략","한글 지원":"미지원","플랫폼":"PC, PS","가격":"패키지구매","개발사":"컬쳐브레인","유통사":"아타리 인터렉티브","일정":"[출시] 1993.12.31 (PC)[출시] 1995.10.25 (PS)","사이트":""},{"게임명":"엑스컴 2: 테러 프롬 더 딥","평점":"0","장르":"전략","한글 지원":"미지원","플랫폼":"PC","가격":"패키지구매","개발사":"컬쳐브레인","유통사":"아타리 인터렉티브","일정":"[출시] 1995.02.28 (PC)","사이트":""}]