[{"게임명":"디스펠","평점":"0","장르":"RPG","한글 지원":"미지원","플랫폼":"PC","가격":"패키지구매","개발사":"아발론스튜디오","유통사":"E2 소프트","일정":"[출시] 2000.05.01 (PC)","사이트":""},{"게임명":"디아블로 2","평점":"10","장르":"RPG","한글 지원":"미지원","플랫폼":"PC","가격":"패키지구매","개발사":"블리자드","유통사":"한빛 소프트","일정":"[출시] 2000.06.30 (PC)","사이트":"http://kr.blizzard.com/ko-kr/games/d2/"},{"게임명":"디제스터","평점":"0","장르":"RPG","한글 지원":"미지원","플랫폼":"PC","가격":"패키지구매","개발사":"리딩엣지","유통사":"","일정":"[출시] 2000.04.15 (PC)","사이트":""},{"게임명":"라스트 가디언 2: 황혼의 봉인","평점":"0","장르":"RPG","한글 지원":"미지원","플랫폼":"PC","가격":"패키지구매","개발사":"안진","유통사":"한국 라이센싱","일정":"[출시] 1999.07.01 (PC)","사이트":""},{"게임명":"라이벌 렐름즈","평점":"0","장르":"전략, 시뮬레이션","한글 지원":"미지원","플랫폼":"PC","가격":"기타","개발사":"타이투스","유통사":"메디아 소프트","일정":"[출시] 1998.12.01 (PC)","사이트":""},{"게임명":"레버넌트","평점":"0","장르":"RPG","한글 지원":"미지원","플랫폼":"PC","가격":"패키지구매","개발사":"시네마틱스","유통사":"판타그램","일정":"[출시] 2000.12.01 (PC)","사이트":""},{"게임명":"레인보우 식스","평점":"0","장르":"FPS","한글 지원":"미지원","플랫폼":"PC, PSN","가격":"패키지구매","개발사":"레드 스톰 엔터테인먼트","유통사":"카마 디지털 엔터테인먼트","일정":"[출시] 1999.01.01 (PC)[출시] 2010.08.24 (PSN)","사이트":""},{"게임명":"레인보우 식스: 로그스피어","평점":"0","장르":"FPS","한글 지원":"미지원","플랫폼":"PC","가격":"패키지구매","개발사":"레드 스톰 엔터테인먼트","유통사":"카마 디지털 엔터테인먼트","일정":"[출시] 1999.08.01 (PC)","사이트":""},{"게임명":"레퀴엠: 어벤징 엔젤","평점":"0","장르":"FPS","한글 지원":"미지원","플랫폼":"PC","가격":"패키지구매","개발사":"사이클론","유통사":"메디아 소프트","일정":"[출시] 1999.04.01 (PC)","사이트":""},{"게임명":"레플리카: 아토믹펑크","평점":"0","장르":"RTS","한글 지원":"미지원","플랫폼":"PC","가격":"패키지구매","개발사":"샘슨코어","유통사":"애니미디어","일정":"[출시] 1999.07.01 (PC)","사이트":""}]